prettyprinter/__init__.py
prettyprinter/color.py
prettyprinter/doc.py
prettyprinter/doctypes.py
prettyprinter/layout.py
prettyprinter/pretty_stdlib.py
prettyprinter/prettyprinter.py
prettyprinter/render.py
prettyprinter/sdoctypes.py
prettyprinter/syntax.py
prettyprinter/utils.py
prettyprinter/extras/__init__.py
prettyprinter/extras/attrs.py
prettyprinter/extras/dataclasses.py
prettyprinter/extras/django.py
prettyprinter/extras/ipython.py
prettyprinter/extras/ipython_repr_pretty.py
prettyprinter/extras/numpy.py
prettyprinter/extras/python.py
prettyprinter/extras/requests.py
prettyprinter-0.18.0.dist-info/DESCRIPTION.rst
prettyprinter-0.18.0.dist-info/METADATA
prettyprinter-0.18.0.dist-info/RECORD
prettyprinter-0.18.0.dist-info/WHEEL
prettyprinter-0.18.0.dist-info/metadata.json
prettyprinter-0.18.0.dist-info/top_level.txt
