Metadata-Version: 1.1
Name: prettyprinter
Version: 0.18.0
Summary: Syntax-highlighting, declarative and composable pretty printer for Python 3.5+
Home-page: https://github.com/tommikaikkonen/prettyprinter
Author: Tommi Kaikkonen
Author-email: kaikkonentommi@gmail.com
License: MIT license
Keywords: prettyprinter
Platform: UNKNOWN
Classifier: Development Status :: 2 - Pre-Alpha
Classifier: Intended Audience :: Developers
Classifier: License :: OSI Approved :: MIT License
Classifier: Natural Language :: English
Classifier: Programming Language :: Python :: 3.6
Classifier: Programming Language :: Python :: 3.5
